setup.cfg
setup.py
pb4py/__init__.py
pb4py/base.py
pb4py/logger.py
pb4py.egg-info/PKG-INFO
pb4py.egg-info/SOURCES.txt
pb4py.egg-info/dependency_links.txt
pb4py.egg-info/requires.txt
pb4py.egg-info/top_level.txt
pb4py/auth/__init__.py
pb4py/auth/base.py
pb4py/auth/basic.py
pb4py/auth/oauth.py