Metadata-Version: 1.1
Name: pb4py
Version: 1.0.0.0
Summary: Python API for PushBullet
Home-page: https://www.sgthotshot.com/pb4py
Author: ['sgthotshot', 'cadyyan']
Author-email: UNKNOWN
License: UNKNOWN
Download-URL: https://github.com/SgtHotshot/pb4py/tarball/1.1
Keywords: PushBullet,notifications,messaging
Platform: UNKNOWN
